[
  {
    "id": "k2p7",
    "provider": "kimi-for-coding",
    "providerName": "Kimi For Coding",
    "displayName": "Kimi K2.7 Code",
    "family": "kimi-k2",
    "releaseDate": "2026-06-12",
    "lastUpdated": "2026-06-12",
    "knowledgeCutoff": "2025-01",
    "contextWindow": 262144,
    "maxOutputTokens": 32768,
    "capabilities": {
      "tools": true,
      "vision": true,
      "reasoning": true,
      "streaming": true,
      "json_mode": true,
      "system_prompt": true,
      "temperature": false,
      "attachment": true,
      "structured_output": true,
      "open_weights": true
    },
    "modalities": {
      "input": [
        "text",
        "image",
        "video"
      ],
      "output": [
        "text"
      ]
    },
    "pricing": {
      "input": 0,
      "output": 0,
      "cacheRead": 0,
      "cacheWrite": 0,
      "currency": "USD",
      "per": 1000000
    },
    "status": "active",
    "deprecationDate": null,
    "replacedBy": null,
    "aliases": [],
    "isAggregator": true,
    "sources": [
      "models.dev"
    ]
  },
  {
    "id": "kimi-k2-thinking",
    "provider": "kimi-for-coding",
    "providerName": "Kimi For Coding",
    "displayName": "Kimi K2 Thinking",
    "family": "kimi-thinking",
    "releaseDate": "2025-11",
    "lastUpdated": "2025-12",
    "knowledgeCutoff": "2025-07",
    "contextWindow": 262144,
    "maxOutputTokens": 32768,
    "capabilities": {
      "tools": true,
      "vision": false,
      "reasoning": true,
      "streaming": true,
      "json_mode": true,
      "system_prompt": true,
      "temperature": true,
      "attachment": false,
      "structured_output": true,
      "open_weights": true
    },
    "modalities": {
      "input": [
        "text"
      ],
      "output": [
        "text"
      ]
    },
    "pricing": {
      "input": 0,
      "output": 0,
      "cacheRead": 0,
      "cacheWrite": 0,
      "currency": "USD",
      "per": 1000000
    },
    "status": "active",
    "deprecationDate": null,
    "replacedBy": null,
    "aliases": [],
    "isAggregator": true,
    "sources": [
      "models.dev"
    ]
  },
  {
    "id": "k2p5",
    "provider": "kimi-for-coding",
    "providerName": "Kimi For Coding",
    "displayName": "Kimi K2.5",
    "family": "kimi-thinking",
    "releaseDate": "2026-01",
    "lastUpdated": "2026-01",
    "knowledgeCutoff": "2025-01",
    "contextWindow": 262144,
    "maxOutputTokens": 32768,
    "capabilities": {
      "tools": true,
      "vision": true,
      "reasoning": true,
      "streaming": true,
      "json_mode": true,
      "system_prompt": true,
      "temperature": true,
      "attachment": false,
      "structured_output": true,
      "open_weights": true
    },
    "modalities": {
      "input": [
        "text",
        "image",
        "video"
      ],
      "output": [
        "text"
      ]
    },
    "pricing": {
      "input": 0,
      "output": 0,
      "cacheRead": 0,
      "cacheWrite": 0,
      "currency": "USD",
      "per": 1000000
    },
    "status": "active",
    "deprecationDate": null,
    "replacedBy": null,
    "aliases": [],
    "isAggregator": true,
    "sources": [
      "models.dev"
    ]
  },
  {
    "id": "k2p6",
    "provider": "kimi-for-coding",
    "providerName": "Kimi For Coding",
    "displayName": "Kimi K2.6",
    "family": "kimi-thinking",
    "releaseDate": "2026-04",
    "lastUpdated": "2026-04",
    "knowledgeCutoff": "2025-01",
    "contextWindow": 262144,
    "maxOutputTokens": 32768,
    "capabilities": {
      "tools": true,
      "vision": true,
      "reasoning": true,
      "streaming": true,
      "json_mode": true,
      "system_prompt": true,
      "temperature": true,
      "attachment": false,
      "structured_output": true,
      "open_weights": true
    },
    "modalities": {
      "input": [
        "text",
        "image",
        "video"
      ],
      "output": [
        "text"
      ]
    },
    "pricing": {
      "input": 0,
      "output": 0,
      "cacheRead": 0,
      "cacheWrite": 0,
      "currency": "USD",
      "per": 1000000
    },
    "status": "active",
    "deprecationDate": null,
    "replacedBy": null,
    "aliases": [],
    "isAggregator": true,
    "sources": [
      "models.dev"
    ]
  }
]